ibmcloudtools/__init__.py
ibmcloudtools/extract.py
ibmcloudtools/ibmcloudtools.py
goatibmcloudtools-2024.7.16.1622.dist-info/METADATA
goatibmcloudtools-2024.7.16.1622.dist-info/WHEEL
goatibmcloudtools-2024.7.16.1622.dist-info/entry_points.txt
goatibmcloudtools-2024.7.16.1622.dist-info/top_level.txt
goatibmcloudtools-2024.7.16.1622.dist-info/RECORD
